MANIFEST.in
README.md
requirements.txt
setup.py
hell123/__init__.py
hell123/main.py
hell123.egg-info/PKG-INFO
hell123.egg-info/SOURCES.txt
hell123.egg-info/dependency_links.txt
hell123.egg-info/entry_points.txt
hell123.egg-info/requires.txt
hell123.egg-info/top_level.txt
hell123/dependencies/__init__.py
hell123/dependencies/dependencies.py
hell123/dependencies/dependency.py
hell123/lib/__init__.py
hell123/lib/args.py
hell123/lib/meditor.py
hell123/lib/srbColour.py
hell123/lib/time.py
hell123/lib/util.py