Metadata-Version: 1.1
Name: hell123
Version: 1.0.5
Summary: A command line tool for media editing
Home-page: http://github.com/srbcheema1/hell123
Author: Sarbjit Singh
Author-email: srbcheema1@gmail.com
License: MIT License
Platform: UNKNOWN
Classifier: Operating System :: POSIX :: Linux
Classifier: License :: OSI Approved :: MIT License
Classifier: Programming Language :: Python :: 3.5
